astro/__init__.py
astro/constants.py
astro/settings.py
astro/dataframe/__init__.py
astro/sql/__init__.py
astro/sql/table.py
astro/sql/operators/__init__.py
astro/sql/operators/agnostic_aggregate_check.py
astro/sql/operators/agnostic_boolean_check.py
astro/sql/operators/agnostic_load_file.py
astro/sql/operators/agnostic_save_file.py
astro/sql/operators/agnostic_sql_append.py
astro/sql/operators/agnostic_sql_merge.py
astro/sql/operators/agnostic_sql_truncate.py
astro/sql/operators/agnostic_stats_check.py
astro/sql/operators/sql_dataframe.py
astro/sql/operators/sql_decorator.py
astro/sql/parsers/__init__.py
astro/sql/parsers/sql_directory_parser.py
astro/utils/__init__.py
astro/utils/bigquery_merge_func.py
astro/utils/cloud_storage_creds.py
astro/utils/database.py
astro/utils/delete.py
astro/utils/dependencies.py
astro/utils/file.py
astro/utils/load.py
astro/utils/path.py
astro/utils/postgres_merge_func.py
astro/utils/postgres_transform.py
astro/utils/schema_util.py
astro/utils/snowflake_append.py
astro/utils/snowflake_merge_func.py
astro/utils/snowflake_transform.py
astro/utils/sqlite_merge_func.py
astro/utils/table_handler.py
astro/utils/task_id_helper.py
astro_projects-0.8.3.dist-info/entry_points.txt
astro_projects-0.8.3.dist-info/LICENSE
astro_projects-0.8.3.dist-info/WHEEL
astro_projects-0.8.3.dist-info/METADATA
astro_projects-0.8.3.dist-info/RECORD
