Metadata-Version: 2.1
Name: astro-projects
Version: 0.8.3
Summary: A decorator that allows users to run SQL queries natively in Airflow.
Keywords: airflow,provider,astronomer,sql,decorator,task flow,elt,etl,dag
Author-email: Astronomer <humans@astronomer.io>
Requires-Python: >=3.7
Classifier: Development Status :: 3 - Alpha
Classifier: License :: OSI Approved :: Apache Software License
Classifier: Programming Language :: Python :: 3
Classifier: Programming Language :: Python :: 3 :: Only
Classifier: Programming Language :: Python :: 3.7
Classifier: Programming Language :: Python :: 3.8
Classifier: Programming Language :: Python :: 3.9
Classifier: Topic :: Database
Requires-Dist: apache-airflow>=2.0
Requires-Dist: python-frontmatter
Requires-Dist: pandas>=1.3.4,<=1.3.5
Requires-Dist: SQLAlchemy>=1.3.18,<=1.3.24
Requires-Dist: markupsafe>=1.1.1,<2.1.0
Requires-Dist: smart-open
Requires-Dist: pyarrow
Requires-Dist: apache-airflow-providers-amazon ; extra == "all"
Requires-Dist: apache-airflow-providers-google>=6.4.0 ; extra == "all"
Requires-Dist: sqlalchemy-bigquery==1.3.0 ; extra == "all"
Requires-Dist: smart-open[all]>=5.2.1 ; extra == "all"
Requires-Dist: s3fs ; extra == "all"
Requires-Dist: apache-airflow-providers-snowflake ; extra == "all"
Requires-Dist: snowflake-sqlalchemy>=1.2.0,<=1.2.4 ; extra == "all"
Requires-Dist: snowflake-connector-python[pandas] ; extra == "all"
Requires-Dist: apache-airflow-providers-postgres ; extra == "all"
Requires-Dist: apache-airflow-providers-amazon ; extra == "amazon"
Requires-Dist: s3fs ; extra == "amazon"
Requires-Dist: smart-open[s3]>=5.2.1 ; extra == "amazon"
Requires-Dist: sphinx==4.4.0 ; extra == "doc"
Requires-Dist: apache-airflow-providers-google ; extra == "google"
Requires-Dist: sqlalchemy-bigquery==1.3.0 ; extra == "google"
Requires-Dist: smart-open[gcs]>=5.2.1 ; extra == "google"
Requires-Dist: apache-airflow-providers-postgres ; extra == "postgres"
Requires-Dist: apache-airflow-providers-snowflake ; extra == "snowflake"
Requires-Dist: snowflake-sqlalchemy>=1.2.0,<=1.2.4 ; extra == "snowflake"
Requires-Dist: snowflake-connector-python[pandas] ; extra == "snowflake"
Requires-Dist: click==8.0.0 ; extra == "tests"
Requires-Dist: pytest>=6.0 ; extra == "tests"
Requires-Dist: pytest-split ; extra == "tests"
Requires-Dist: pytest-dotenv ; extra == "tests"
Requires-Dist: requests-mock ; extra == "tests"
Requires-Dist: pytest-cov ; extra == "tests"
Requires-Dist: pytest-describe ; extra == "tests"
Requires-Dist: mypy ; extra == "tests"
Requires-Dist: sqlalchemy-stubs ; extra == "tests"
Project-URL: Home, https://astronomer.io/
Provides-Extra: all
Provides-Extra: amazon
Provides-Extra: doc
Provides-Extra: google
Provides-Extra: postgres
Provides-Extra: snowflake
Provides-Extra: tests
